app.py
commands/__init__.py
commands/add.py
commands/change.py
commands/current.py
commands/delete.py
commands/done.py
commands/hide.py
commands/import_tapd.py
commands/init.py
commands/list.py
commands/move.py
commands/rename.py
commands/search.py
commands/stats.py
core/__init__.py
core/data.py
core/git.py
todo_task_node_tree-0.1.1.dist-info/METADATA
todo_task_node_tree-0.1.1.dist-info/WHEEL
todo_task_node_tree-0.1.1.dist-info/entry_points.txt
todo_task_node_tree-0.1.1.dist-info/top_level.txt
todo_task_node_tree-0.1.1.dist-info/RECORD
