Metadata-Version: 2.4
Name: todo-task-node-tree
Version: 0.1.1
Summary: 📌 基于 Typer 与 Rich 的命令行 Todo 工具
Home-page: https://github.com/RinKokawa/todo-cli
Author: RinKokokawa
Author-email: rin@rinco.cc
License: MIT
Classifier: Programming Language :: Python :: 3
Classifier: License :: OSI Approved :: MIT License
Classifier: Operating System :: OS Independent
Requires-Python: >=3.13
Requires-Dist: typer>=0.7.0
Requires-Dist: rich>=10.0.0
Dynamic: author
Dynamic: author-email
Dynamic: classifier
Dynamic: description
Dynamic: description-content-type
Dynamic: home-page
Dynamic: license
Dynamic: requires-dist
Dynamic: requires-python
Dynamic: summary
